qai/__init__.py
qai/issues.py
qai/server.py
qai/spacy_factor.py
qai/util.py
qai/validation.py
qai-5.1.1.dist-info/WHEEL
qai-5.1.1.dist-info/METADATA
qai-5.1.1.dist-info/RECORD
