Metadata-Version: 2.1
Name: qai
Version: 5.1.1
Summary: Helper functions and classes for interacting with the rest of the Writer platform
License: Proprietary
Author: Sam Havens
Author-email: sam.havens@writer.com
Requires-Python: >=3.8,<4.0
Classifier: License :: Other/Proprietary License
Classifier: Programming Language :: Python :: 3
Classifier: Programming Language :: Python :: 3.8
Classifier: Programming Language :: Python :: 3.9
Requires-Dist: sanic (>=21.3.4,<22.0.0)
